{
  "order": {
    "ordernummer": "2004-279",
    "orderdatum": "19-11-2023",
    "betaaltermijn": "30-dagen",
    "klant": {
      "naam": "PC Jupiter B.V.",
      "adres": "Hoofdstraat 815",
      "postcode": "1328 AB",
      "stad": "Amsterdam",
      "KVK-nummer": "74837782"
    },
    "producten": [
      {
        "productnaam": "Oracle VirtualBox",
        "aantal": 2,
        "prijs_per_stuk_excl_btw": 41.68,
        "btw_percentage": 21.0
      },
      {
        "productnaam": "Microsoft Office 365",
        "aantal": 3,
        "prijs_per_stuk_excl_btw": 92.27,
        "btw_percentage": 21.0
      },
      {
        "productnaam": "Oracle VM",
        "aantal": 1,
        "prijs_per_stuk_excl_btw": 22.71,
        "btw_percentage": 21.0
      },
      {
        "productnaam": "Google Analytics",
        "aantal": 3,
        "prijs_per_stuk_excl_btw": 234.98,
        "btw_percentage": 21.0
      },
      {
        "productnaam": "Microsoft SQL Server 2019",
        "aantal": 2,
        "prijs_per_stuk_excl_btw": 448.14,
        "btw_percentage": 21.0
      },
      {
        "productnaam": "Google Analytics",
        "aantal": 3,
        "prijs_per_stuk_excl_btw": 338.28,
        "btw_percentage": 21.0
      },
      {
        "productnaam": "Adobe Illustrator",
        "aantal": 1,
        "prijs_per_stuk_excl_btw": 387.38,
        "btw_percentage": 21.0
      },
      {
        "productnaam": "Microsoft Power BI",
        "aantal": 1,
        "prijs_per_stuk_excl_btw": 67.37,
        "btw_percentage": 21.0
      },
      {
        "productnaam": "Google Webservices",
        "aantal": 3,
        "prijs_per_stuk_excl_btw": 358.32,
        "btw_percentage": 21.0
      },
      {
        "productnaam": "Google Workspace",
        "aantal": 5,
        "prijs_per_stuk_excl_btw": 417.09,
        "btw_percentage": 21.0
      },
      {
        "productnaam": "Google Analytics",
        "aantal": 1,
        "prijs_per_stuk_excl_btw": 304.46,
        "btw_percentage": 21.0
      }
    ]
  }
}