{
  "order": {
    "ordernummer": "2010-227",
    "orderdatum": "05-06-2024",
    "betaaltermijn": "30-dagen",
    "klant": {
      "naam": "PC Neptunus B.V.",
      "adres": "Kerkstraat 65",
      "postcode": "5922 AB",
      "stad": "Amsterdam",
      "KVK-nummer": "26002831"
    },
    "producten": [
      {
        "productnaam": "Google Ads",
        "aantal": 3,
        "prijs_per_stuk_excl_btw": 167.3,
        "btw_percentage": 21.0
      },
      {
        "productnaam": "Google Webservices",
        "aantal": 2,
        "prijs_per_stuk_excl_btw": 447.71,
        "btw_percentage": 21.0
      },
      {
        "productnaam": "Microsoft Windows 10",
        "aantal": 2,
        "prijs_per_stuk_excl_btw": 468.36,
        "btw_percentage": 21.0
      },
      {
        "productnaam": "GitHub",
        "aantal": 4,
        "prijs_per_stuk_excl_btw": 355.52,
        "btw_percentage": 21.0
      },
      {
        "productnaam": "Google Webservices",
        "aantal": 3,
        "prijs_per_stuk_excl_btw": 393.16,
        "btw_percentage": 21.0
      },
      {
        "productnaam": "Oracle VM",
        "aantal": 4,
        "prijs_per_stuk_excl_btw": 54.22,
        "btw_percentage": 21.0
      },
      {
        "productnaam": "Oracle WebLogic Server",
        "aantal": 2,
        "prijs_per_stuk_excl_btw": 196.42,
        "btw_percentage": 21.0
      },
      {
        "productnaam": "Oracle Solaris",
        "aantal": 5,
        "prijs_per_stuk_excl_btw": 143.7,
        "btw_percentage": 21.0
      },
      {
        "productnaam": "Microsoft Visual Studio 2019",
        "aantal": 4,
        "prijs_per_stuk_excl_btw": 90.89,
        "btw_percentage": 21.0
      },
      {
        "productnaam": "Oracle Cloud",
        "aantal": 3,
        "prijs_per_stuk_excl_btw": 359.35,
        "btw_percentage": 21.0
      },
      {
        "productnaam": "Google Ads",
        "aantal": 1,
        "prijs_per_stuk_excl_btw": 59.08,
        "btw_percentage": 21.0
      },
      {
        "productnaam": "Microsoft Windows 10",
        "aantal": 5,
        "prijs_per_stuk_excl_btw": 79.09,
        "btw_percentage": 21.0
      }
    ]
  }
}