{
  "order": {
    "ordernummer": "2015-981",
    "orderdatum": "15-08-2021",
    "betaaltermijn": "60-dagen",
    "klant": {
      "naam": "PC Neptunus B.V.",
      "adres": "Hoofdstraat 72",
      "postcode": "5096 AA",
      "stad": "Rotterdam",
      "KVK-nummer": "49391399"
    },
    "producten": [
      {
        "productnaam": "Adobe InDesign",
        "aantal": 3,
        "prijs_per_stuk_excl_btw": 258.44,
        "btw_percentage": 21.0
      },
      {
        "productnaam": "Adobe Illustrator",
        "aantal": 3,
        "prijs_per_stuk_excl_btw": 456.87,
        "btw_percentage": 21.0
      },
      {
        "productnaam": "Microsoft Dynamics 365",
        "aantal": 1,
        "prijs_per_stuk_excl_btw": 96.98,
        "btw_percentage": 21.0
      },
      {
        "productnaam": "Oracle Cloud",
        "aantal": 5,
        "prijs_per_stuk_excl_btw": 210.97,
        "btw_percentage": 21.0
      },
      {
        "productnaam": "Oracle VirtualBox",
        "aantal": 3,
        "prijs_per_stuk_excl_btw": 145.13,
        "btw_percentage": 21.0
      },
      {
        "productnaam": "Microsoft Power BI",
        "aantal": 2,
        "prijs_per_stuk_excl_btw": 300.92,
        "btw_percentage": 21.0
      },
      {
        "productnaam": "Google Cloud Platform",
        "aantal": 4,
        "prijs_per_stuk_excl_btw": 368.97,
        "btw_percentage": 21.0
      },
      {
        "productnaam": "GitHub",
        "aantal": 4,
        "prijs_per_stuk_excl_btw": 129.08,
        "btw_percentage": 21.0
      },
      {
        "productnaam": "Adobe Premiere Pro",
        "aantal": 2,
        "prijs_per_stuk_excl_btw": 294.16,
        "btw_percentage": 21.0
      },
      {
        "productnaam": "Oracle Database 19c",
        "aantal": 4,
        "prijs_per_stuk_excl_btw": 242.35,
        "btw_percentage": 21.0
      },
      {
        "productnaam": "Microsoft Visual Studio 2019",
        "aantal": 5,
        "prijs_per_stuk_excl_btw": 171.23,
        "btw_percentage": 21.0
      },
      {
        "productnaam": "Microsoft Windows Server 2019",
        "aantal": 3,
        "prijs_per_stuk_excl_btw": 318.97,
        "btw_percentage": 21.0
      }
    ]
  }
}