{
  "order": {
    "ordernummer": "2021-184",
    "orderdatum": "23-08-2022",
    "betaaltermijn": "60-dagen",
    "klant": {
      "naam": "PC Mercurius B.V.",
      "adres": "Schoolstraat 898",
      "postcode": "4678 AB",
      "stad": "Amsterdam",
      "KVK-nummer": "36752051"
    },
    "producten": [
      {
        "productnaam": "Oracle VM",
        "aantal": 4,
        "prijs_per_stuk_excl_btw": 227.85,
        "btw_percentage": 21.0
      },
      {
        "productnaam": "Microsoft Power BI",
        "aantal": 4,
        "prijs_per_stuk_excl_btw": 326.71,
        "btw_percentage": 21.0
      },
      {
        "productnaam": "Microsoft Windows Server 2019",
        "aantal": 3,
        "prijs_per_stuk_excl_btw": 297.67,
        "btw_percentage": 21.0
      },
      {
        "productnaam": "Oracle Java SE",
        "aantal": 2,
        "prijs_per_stuk_excl_btw": 186.51,
        "btw_percentage": 21.0
      },
      {
        "productnaam": "Oracle Solaris",
        "aantal": 2,
        "prijs_per_stuk_excl_btw": 307.14,
        "btw_percentage": 21.0
      },
      {
        "productnaam": "Google Cloud Platform",
        "aantal": 4,
        "prijs_per_stuk_excl_btw": 181.49,
        "btw_percentage": 21.0
      }
    ]
  }
}