{
  "order": {
    "ordernummer": "2023-186",
    "orderdatum": "23-08-2022",
    "betaaltermijn": "30-dagen",
    "klant": {
      "naam": "PC Jupiter B.V.",
      "adres": "Hoofdstraat 267",
      "postcode": "3143 AC",
      "stad": "Rotterdam",
      "KVK-nummer": "95122479"
    },
    "producten": [
      {
        "productnaam": "Oracle VirtualBox",
        "aantal": 1,
        "prijs_per_stuk_excl_btw": 249.72,
        "btw_percentage": 21.0
      },
      {
        "productnaam": "Microsoft Azure",
        "aantal": 5,
        "prijs_per_stuk_excl_btw": 210.1,
        "btw_percentage": 21.0
      },
      {
        "productnaam": "Oracle WebLogic Server",
        "aantal": 3,
        "prijs_per_stuk_excl_btw": 248.78,
        "btw_percentage": 21.0
      },
      {
        "productnaam": "Oracle Java SE",
        "aantal": 2,
        "prijs_per_stuk_excl_btw": 218.32,
        "btw_percentage": 21.0
      },
      {
        "productnaam": "Google Workspace",
        "aantal": 1,
        "prijs_per_stuk_excl_btw": 313.17,
        "btw_percentage": 21.0
      },
      {
        "productnaam": "Microsoft Office 365",
        "aantal": 3,
        "prijs_per_stuk_excl_btw": 94.75,
        "btw_percentage": 21.0
      },
      {
        "productnaam": "Oracle MySQL",
        "aantal": 1,
        "prijs_per_stuk_excl_btw": 47.63,
        "btw_percentage": 21.0
      },
      {
        "productnaam": "Adobe Creative Cloud",
        "aantal": 5,
        "prijs_per_stuk_excl_btw": 381.13,
        "btw_percentage": 21.0
      },
      {
        "productnaam": "Microsoft SQL Server 2019",
        "aantal": 3,
        "prijs_per_stuk_excl_btw": 21.86,
        "btw_percentage": 21.0
      },
      {
        "productnaam": "Adobe Illustrator",
        "aantal": 3,
        "prijs_per_stuk_excl_btw": 464.39,
        "btw_percentage": 21.0
      },
      {
        "productnaam": "Adobe InDesign",
        "aantal": 4,
        "prijs_per_stuk_excl_btw": 402.99,
        "btw_percentage": 21.0
      },
      {
        "productnaam": "Adobe Photoshop",
        "aantal": 2,
        "prijs_per_stuk_excl_btw": 159.55,
        "btw_percentage": 21.0
      },
      {
        "productnaam": "Microsoft Windows 10",
        "aantal": 2,
        "prijs_per_stuk_excl_btw": 449.42,
        "btw_percentage": 21.0
      },
      {
        "productnaam": "Adobe Premiere Pro",
        "aantal": 1,
        "prijs_per_stuk_excl_btw": 458.6,
        "btw_percentage": 21.0
      },
      {
        "productnaam": "Google Ads",
        "aantal": 1,
        "prijs_per_stuk_excl_btw": 176.98,
        "btw_percentage": 21.0
      },
      {
        "productnaam": "Oracle Java SE",
        "aantal": 5,
        "prijs_per_stuk_excl_btw": 445.84,
        "btw_percentage": 21.0
      }
    ]
  }
}