{
  "order": {
    "ordernummer": "2023-731",
    "orderdatum": "04-05-2023",
    "betaaltermijn": "60-dagen",
    "klant": {
      "naam": "PC Aarde B.V.",
      "adres": "Schoolstraat 176",
      "postcode": "4701 AC",
      "stad": "Amsterdam",
      "KVK-nummer": "67254730"
    },
    "producten": [
      {
        "productnaam": "Microsoft Office 365",
        "aantal": 3,
        "prijs_per_stuk_excl_btw": 22.11,
        "btw_percentage": 21.0
      },
      {
        "productnaam": "Microsoft Windows 10",
        "aantal": 2,
        "prijs_per_stuk_excl_btw": 421.16,
        "btw_percentage": 21.0
      },
      {
        "productnaam": "Google Analytics",
        "aantal": 4,
        "prijs_per_stuk_excl_btw": 76.34,
        "btw_percentage": 21.0
      },
      {
        "productnaam": "Microsoft Windows Server 2019",
        "aantal": 5,
        "prijs_per_stuk_excl_btw": 275.22,
        "btw_percentage": 21.0
      },
      {
        "productnaam": "Google Ads",
        "aantal": 3,
        "prijs_per_stuk_excl_btw": 115.45,
        "btw_percentage": 21.0
      },
      {
        "productnaam": "Oracle Cloud",
        "aantal": 5,
        "prijs_per_stuk_excl_btw": 328.24,
        "btw_percentage": 21.0
      },
      {
        "productnaam": "Adobe Premiere Pro",
        "aantal": 1,
        "prijs_per_stuk_excl_btw": 16.11,
        "btw_percentage": 21.0
      },
      {
        "productnaam": "Microsoft Power BI",
        "aantal": 5,
        "prijs_per_stuk_excl_btw": 171.43,
        "btw_percentage": 21.0
      },
      {
        "productnaam": "Google Ads",
        "aantal": 5,
        "prijs_per_stuk_excl_btw": 374.57,
        "btw_percentage": 21.0
      },
      {
        "productnaam": "Microsoft Office 365",
        "aantal": 5,
        "prijs_per_stuk_excl_btw": 496.41,
        "btw_percentage": 21.0
      },
      {
        "productnaam": "Oracle Cloud",
        "aantal": 5,
        "prijs_per_stuk_excl_btw": 112.18,
        "btw_percentage": 21.0
      },
      {
        "productnaam": "Google Analytics",
        "aantal": 4,
        "prijs_per_stuk_excl_btw": 62.48,
        "btw_percentage": 21.0
      },
      {
        "productnaam": "Microsoft Visual Studio 2019",
        "aantal": 3,
        "prijs_per_stuk_excl_btw": 299.2,
        "btw_percentage": 21.0
      },
      {
        "productnaam": "Microsoft Office 365",
        "aantal": 3,
        "prijs_per_stuk_excl_btw": 75.53,
        "btw_percentage": 21.0
      }
    ]
  }
}