{
  "order": {
    "ordernummer": "2024-011",
    "orderdatum": "19-06-2024",
    "betaaltermijn": "60-dagen",
    "klant": {
      "naam": "PC Neptunus B.V.",
      "adres": "Kerkstraat 877",
      "postcode": "2928 AB",
      "stad": "Utrecht",
      "KVK-nummer": "16982371"
    },
    "producten": [
      {
        "productnaam": "Google Cloud Platform",
        "aantal": 3,
        "prijs_per_stuk_excl_btw": 10.1,
        "btw_percentage": 21.0
      },
      {
        "productnaam": "Oracle Cloud",
        "aantal": 5,
        "prijs_per_stuk_excl_btw": 151.53,
        "btw_percentage": 21.0
      },
      {
        "productnaam": "Oracle VM",
        "aantal": 2,
        "prijs_per_stuk_excl_btw": 142.41,
        "btw_percentage": 21.0
      },
      {
        "productnaam": "Microsoft Office 365",
        "aantal": 2,
        "prijs_per_stuk_excl_btw": 109.37,
        "btw_percentage": 21.0
      },
      {
        "productnaam": "Microsoft Windows 10",
        "aantal": 1,
        "prijs_per_stuk_excl_btw": 261.8,
        "btw_percentage": 21.0
      },
      {
        "productnaam": "Adobe Photoshop",
        "aantal": 2,
        "prijs_per_stuk_excl_btw": 282.49,
        "btw_percentage": 21.0
      },
      {
        "productnaam": "Microsoft Windows Server 2019",
        "aantal": 3,
        "prijs_per_stuk_excl_btw": 92.33,
        "btw_percentage": 21.0
      },
      {
        "productnaam": "Oracle Cloud",
        "aantal": 5,
        "prijs_per_stuk_excl_btw": 451.75,
        "btw_percentage": 21.0
      },
      {
        "productnaam": "Microsoft Visual Studio 2019",
        "aantal": 5,
        "prijs_per_stuk_excl_btw": 184.25,
        "btw_percentage": 21.0
      },
      {
        "productnaam": "Adobe InDesign",
        "aantal": 5,
        "prijs_per_stuk_excl_btw": 99.85,
        "btw_percentage": 21.0
      },
      {
        "productnaam": "Microsoft SQL Server 2019",
        "aantal": 1,
        "prijs_per_stuk_excl_btw": 383.03,
        "btw_percentage": 21.0
      },
      {
        "productnaam": "Microsoft Azure",
        "aantal": 4,
        "prijs_per_stuk_excl_btw": 147.17,
        "btw_percentage": 21.0
      },
      {
        "productnaam": "Microsoft Windows 10",
        "aantal": 4,
        "prijs_per_stuk_excl_btw": 232.71,
        "btw_percentage": 21.0
      },
      {
        "productnaam": "Microsoft Visual Studio 2019",
        "aantal": 5,
        "prijs_per_stuk_excl_btw": 115.55,
        "btw_percentage": 21.0
      },
      {
        "productnaam": "Microsoft Dynamics 365",
        "aantal": 2,
        "prijs_per_stuk_excl_btw": 477.96,
        "btw_percentage": 21.0
      },
      {
        "productnaam": "Adobe Photoshop",
        "aantal": 2,
        "prijs_per_stuk_excl_btw": 75.68,
        "btw_percentage": 21.0
      },
      {
        "productnaam": "Microsoft Office 365",
        "aantal": 4,
        "prijs_per_stuk_excl_btw": 35.93,
        "btw_percentage": 21.0
      },
      {
        "productnaam": "Microsoft Power BI",
        "aantal": 1,
        "prijs_per_stuk_excl_btw": 73.77,
        "btw_percentage": 21.0
      }
    ]
  }
}